tlrx_test_engine/__init__.py
tlrx_test_engine/__main__.py
tlrx_test_engine/converters/data_converter.py
tlrx_test_engine/interfaces/__init__.py
tlrx_test_engine/interfaces/ialgorithm.py
tlrx_test_engine/interfaces/iconverter.py
tlrx_test_engine/interfaces/idata.py
tlrx_test_engine/interfaces/imodel.py
tlrx_test_engine/interfaces/ipipeline.py
tlrx_test_engine/interfaces/iplugin.py
tlrx_test_engine/interfaces/iserializer.py
tlrx_test_engine/interfaces/itestresult.py
tlrx_test_engine/io/__init__.py
tlrx_test_engine/io/delimiterdata/__init__.py
tlrx_test_engine/io/delimiterdata/delimiterdata.py
tlrx_test_engine/io/delimiterserializer/__init__.py
tlrx_test_engine/io/delimiterserializer/delimiterserializer.py
tlrx_test_engine/io/imagedata/__init__.py
tlrx_test_engine/io/imagedata/imagedata.py
tlrx_test_engine/io/imageserializer/__init__.py
tlrx_test_engine/io/imageserializer/imageserializer.py
tlrx_test_engine/io/joblibserializer/__init__.py
tlrx_test_engine/io/joblibserializer/joblibserializer.py
tlrx_test_engine/io/lightgbmmodel/__init__.py
tlrx_test_engine/io/lightgbmmodel/lightgbmmodel.py
tlrx_test_engine/io/openapiconnector/__init__.py
tlrx_test_engine/io/openapiconnector/openapiconnector.py
tlrx_test_engine/io/pandasdata/__init__.py
tlrx_test_engine/io/pandasdata/pandasdata.py
tlrx_test_engine/io/pickleserializer/__init__.py
tlrx_test_engine/io/pickleserializer/pickleserializer.py
tlrx_test_engine/io/sklearnmodel/__init__.py
tlrx_test_engine/io/sklearnmodel/sklearnmodel.py
tlrx_test_engine/io/sklearnpipeline/__init__.py
tlrx_test_engine/io/sklearnpipeline/sklearnpipeline.py
tlrx_test_engine/io/tensorflowmodel/__init__.py
tlrx_test_engine/io/tensorflowmodel/tensorflowmodel.py
tlrx_test_engine/io/tensorflowserializer/__init__.py
tlrx_test_engine/io/tensorflowserializer/tensorflowserializer.py
tlrx_test_engine/io/xgboostmodel/__init__.py
tlrx_test_engine/io/xgboostmodel/xgboostmodel.py
tlrx_test_engine/logging/__init__.py
tlrx_test_engine/logging/error.py
tlrx_test_engine-2.0.0a1.dist-info/METADATA
tlrx_test_engine-2.0.0a1.dist-info/WHEEL
tlrx_test_engine-2.0.0a1.dist-info/licenses/AUTHORS.rst
tlrx_test_engine-2.0.0a1.dist-info/licenses/LICENSE
tlrx_test_engine-2.0.0a1.dist-info/RECORD
